__init__.py
zenbase_llml/__init__.py
zenbase_llml/llml.py
zenbase_llml/formatters/__init__.py
zenbase_llml/formatters/json.py
zenbase_llml/formatters/types.py
zenbase_llml/formatters/base/__init__.py
zenbase_llml/formatters/base/base_model.py
zenbase_llml/formatters/base/bool.py
zenbase_llml/formatters/base/dataclass.py
zenbase_llml/formatters/base/datetime.py
zenbase_llml/formatters/base/fallback.py
zenbase_llml/formatters/base/float.py
zenbase_llml/formatters/base/int.py
zenbase_llml/formatters/base/none.py
zenbase_llml/formatters/base/str.py
zenbase_llml/formatters/base/timedelta.py
zenbase_llml/formatters/vibe_xml/__init__.py
zenbase_llml/formatters/vibe_xml/dict.py
zenbase_llml/formatters/vibe_xml/helpers.py
zenbase_llml/formatters/vibe_xml/list.py
zenbase_llml-0.4.0.dist-info/METADATA
zenbase_llml-0.4.0.dist-info/WHEEL
zenbase_llml-0.4.0.dist-info/top_level.txt
zenbase_llml-0.4.0.dist-info/RECORD
