Metadata-Version: 2.4
Name: zenbase_llml
Version: 0.4.0
Summary: A lightweight markup language for structured text generation
Author-email: Cyrus <cyrus@zenbase.ai>
License: MIT
Project-URL: Homepage, https://github.com/zenbase-ai/llml
Project-URL: Repository, https://github.com/zenbase-ai/llml
Project-URL: Issues, https://github.com/zenbase-ai/llml/issues
Classifier: Development Status :: 4 - Beta
Classifier: Intended Audience :: Developers
Classifier: License :: OSI Approved :: MIT License
Classifier: Programming Language :: Python :: 3
Classifier: Programming Language :: Python :: 3.8
Classifier: Programming Language :: Python :: 3.9
Classifier: Programming Language :: Python :: 3.10
Classifier: Programming Language :: Python :: 3.11
Classifier: Programming Language :: Python :: 3.12
Classifier: Programming Language :: Python :: 3.13
Classifier: Topic :: Software Development :: Libraries :: Python Modules
Classifier: Topic :: Text Processing :: Markup
Requires-Python: >=3.8
Provides-Extra: dev
Requires-Dist: pytest>=6.0; extra == "dev"
Requires-Dist: pytest-cov; extra == "dev"
Requires-Dist: tox; extra == "dev"
Requires-Dist: ruff; extra == "dev"
